LICENSE
README.md
setup.py
pygtools/__init__.py
pygtools/screenmanager.py
pygtools.egg-info/PKG-INFO
pygtools.egg-info/SOURCES.txt
pygtools.egg-info/dependency_links.txt
pygtools.egg-info/requires.txt
pygtools.egg-info/top_level.txt