Metadata-Version: 2.1
Name: pygtools
Version: 1.0.0.dev2
Summary: This is a small plugin for pygame, which provides some tools to make creating games with pygame easier. The package is still incomplete as just one module, the screenmanager which makes it easier to create scenes in pygame.
Home-page: https://github.com/Jefferson5286/PgTools.git
Author: Jefferson Lima
Author-email: jeffersonlima5286@gmail.com
License: MIT License
Keywords: screen for pygame
Platform: UNKNOWN
License-File: LICENSE
